dash_pydantic_form/__init__.py
dash_pydantic_form/form_section.py
dash_pydantic_form/i18n.py
dash_pydantic_form/ids.py
dash_pydantic_form/model_form.py
dash_pydantic_form/pydf_aggrid.js
dash_pydantic_form/pydf_clientside.js
dash_pydantic_form/pydf_styles.css
dash_pydantic_form/utils.py
dash_pydantic_form/fields/__init__.py
dash_pydantic_form/fields/all_fields.py
dash_pydantic_form/fields/base_fields.py
dash_pydantic_form/fields/dict_field.py
dash_pydantic_form/fields/list_field.py
dash_pydantic_form/fields/markdown_field.py
dash_pydantic_form/fields/model_field.py
dash_pydantic_form/fields/path_field.py
dash_pydantic_form/fields/quantity_field.py
dash_pydantic_form/fields/table_field.py
dash_pydantic_form/fields/transferlist_field.py
dash_pydantic_form/form_layouts/__init__.py
dash_pydantic_form/form_layouts/accordion_form_layout.py
dash_pydantic_form/form_layouts/form_layout.py
dash_pydantic_form/form_layouts/steps_form_layout.py
dash_pydantic_form/form_layouts/tabs_form_layout.py
dash_pydantic_form/locales/pydf.pot
dash_pydantic_form/locales/en/LC_MESSAGES/pydf.po
dash_pydantic_form/locales/fr/LC_MESSAGES/pydf.po
dash_pydantic_form-0.18.3.dist-info/METADATA
dash_pydantic_form-0.18.3.dist-info/WHEEL
dash_pydantic_form-0.18.3.dist-info/licenses/LICENSE
dash_pydantic_form-0.18.3.dist-info/RECORD
