Metadata-Version: 2.4
Name: dash-pydantic-form
Version: 0.18.3
Summary: Create Dash forms from pydantic objects
Project-URL: Homepage, https://pydf-docs.onrender.com
Project-URL: Source, https://github.com/RenaudLN/dash-pydantic-form
Author-email: Renaud Lainé <renaudlaine31@gmail.com>
License: The MIT License (MIT)
License-File: LICENSE
Requires-Python: <3.14,>=3.10
Requires-Dist: dash-ag-grid>=31
Requires-Dist: dash-iconify
Requires-Dist: dash-mantine-components<3,>=0.15
Requires-Dist: dash-pydantic-utils
Requires-Dist: dash<4,>=2.16
Requires-Dist: fsspec
Requires-Dist: pydantic==2.*
Provides-Extra: dev
Requires-Dist: dash[testing]; extra == 'dev'
Requires-Dist: pre-commit; extra == 'dev'
Requires-Dist: pytest; extra == 'dev'
